package_scgps_speak/__init__.py
package_scgps_speak/__version__.py
package_scgps_speak/core.py
package_scgps_speak-0.1.0.dist-info/LICENSE
package_scgps_speak-0.1.0.dist-info/METADATA
package_scgps_speak-0.1.0.dist-info/WHEEL
package_scgps_speak-0.1.0.dist-info/top_level.txt
package_scgps_speak-0.1.0.dist-info/RECORD
